font_name_tool/__init__.py
font_name_tool/cli.py
font_name_tool/dump_codes.py
font_name_tool-0.1.2.dist-info/LICENSE
font_name_tool-0.1.2.dist-info/METADATA
font_name_tool-0.1.2.dist-info/WHEEL
font_name_tool-0.1.2.dist-info/entry_points.txt
font_name_tool-0.1.2.dist-info/RECORD
