Metadata-Version: 2.1
Name: font-name-tool
Version: 0.1.2
Summary: CLI tool for reading and writing the name table in TTF and OTF fonts
Home-page: https://github.com/andrewsuzuki/font-name-tool
License: MIT
Author: Andrew Suzuki
Requires-Python: >=3.8.1,<4.0.0
Classifier: Development Status :: 3 - Alpha
Classifier: License :: OSI Approved :: MIT License
Classifier: Operating System :: OS Independent
Classifier: Programming Language :: Python :: 3
Classifier: Programming Language :: Python :: 3.9
Classifier: Programming Language :: Python :: 3.10
Classifier: Programming Language :: Python :: 3.11
Classifier: Programming Language :: Python :: 3.12
Classifier: Programming Language :: Python :: 3.13
Classifier: Topic :: File Formats
Classifier: Topic :: Utilities
Requires-Dist: fonttools (>=4.55.3,<5.0.0)
Project-URL: Repository, https://github.com/andrewsuzuki/font-name-tool
